edtime
