Metadata-Version: 2.1
Name: edtime
Version: 0.9.5
Summary: Extended Decimal Time
Home-page: https://github.com/mindey/edtime
Author: Mindey
Author-email: ~@mindey.com
License: MIT
Platform: UNKNOWN
Provides-Extra: test
